LICENSE
MANIFEST.in
README.rst
example.conf
flask_multistatic.py
setup.py
flask_multistatic.egg-info/PKG-INFO
flask_multistatic.egg-info/SOURCES.txt
flask_multistatic.egg-info/dependency_links.txt
flask_multistatic.egg-info/requires.txt
flask_multistatic.egg-info/top_level.txt