Metadata-Version: 1.1
Name: flask-multistatic
Version: 1.0
Summary: Simple flask plugin to allow overriding static files
Home-page: https://pagure.io/flask-multistatic
Author: Pierre-Yves Chibon
Author-email: pingou@pingoured.fr
License: GPLv3+
Download-URL: https://pagure.io/releases/flask-multistatic/
Platform: UNKNOWN
Classifier: Development Status :: 5 - Production/Stable
Classifier: Intended Audience :: Developers
Classifier: License :: OSI Approved :: GNU General Public License v3 or later (GPLv3+)
Classifier: Operating System :: OS Independent
Classifier: Programming Language :: Python :: 2.6
Classifier: Programming Language :: Python :: 2.7
Classifier: Programming Language :: Python :: 3
Classifier: Topic :: Software Development :: Libraries
